README.rst
setup.py
influx_sansio/__init__.py
influx_sansio/abc.py
influx_sansio/asks.py
influx_sansio/http.py
influx_sansio/serialization.py
influx_sansio/testing_utils.py
influx_sansio.egg-info/PKG-INFO
influx_sansio.egg-info/SOURCES.txt
influx_sansio.egg-info/dependency_links.txt
influx_sansio.egg-info/requires.txt
influx_sansio.egg-info/top_level.txt