Metadata-Version: 1.2
Name: influx-sansio
Version: 0.1.0
Summary: SansIO Python client for InfluxDB
Home-page: https://github.com/miracle2k/influx-sansio
Author: Michael Elsdorfer
Author-email: michael@elsdoerfer.com
License: UNKNOWN
Platform: UNKNOWN
Classifier: Development Status :: 4 - Beta
Classifier: Intended Audience :: Developers
Classifier: License :: OSI Approved :: MIT License
Classifier: Programming Language :: Python :: 3.6
Classifier: Topic :: Database
Requires-Python: >=3.6
